{
  "schema_version": "1.0.0",
  "specs": [
    {
      "id": "001-foundation-v0-1",
      "version": "1.0.0",
      "status": "approved",
      "immutable": true,
      "path": "specs/001-foundation-v0-1/spec.md",
      "governs": [
        "README.md",
        ".specify/memory/constitution.md",
        "docs/quality-standards.md",
        "docs/compatibility-policy.md",
        "docs/exception-process.md",
        "crates/cogolo-cli/",
        "crates/traverse-cli/",
        "crates/cogolo-mcp/",
        "crates/traverse-mcp/"
      ]
    },
    {
      "id": "002-capability-contracts",
      "version": "1.0.0",
      "status": "approved",
      "immutable": true,
      "path": "specs/002-capability-contracts/spec.md",
      "governs": [
        "crates/cogolo-contracts/",
        "crates/traverse-contracts/"
      ]
    },
    {
      "id": "003-event-contracts",
      "version": "1.0.0",
      "status": "approved",
      "immutable": true,
      "path": "specs/003-event-contracts/spec.md",
      "governs": [
        "crates/cogolo-contracts/",
        "crates/traverse-contracts/"
      ]
    },
    {
      "id": "004-spec-alignment-gate",
      "version": "1.0.0",
      "status": "approved",
      "immutable": true,
      "path": "specs/004-spec-alignment-gate/spec.md",
      "governs": [
        ".github/workflows/ci.yml",
        "scripts/ci/",
        "specs/governance/"
      ]
    },
    {
      "id": "005-capability-registry",
      "version": "1.0.0",
      "status": "approved",
      "immutable": true,
      "path": "specs/005-capability-registry/spec.md",
      "governs": [
        "crates/cogolo-registry/",
        "crates/traverse-registry/"
      ]
    },
    {
      "id": "006-runtime-request-execution",
      "version": "1.0.0",
      "status": "approved",
      "immutable": true,
      "path": "specs/006-runtime-request-execution/spec.md",
      "governs": [
        "crates/cogolo-runtime/",
        "crates/traverse-runtime/"
      ]
    },
    {
      "id": "007-workflow-registry-traversal",
      "version": "1.0.0",
      "status": "approved",
      "immutable": true,
      "path": "specs/007-workflow-registry-traversal/spec.md",
      "governs": [
        "crates/cogolo-registry/",
        "crates/traverse-registry/",
        "crates/cogolo-runtime/",
        "crates/traverse-runtime/"
      ]
    },
    {
      "id": "008-expedition-example-domain",
      "version": "1.0.0",
      "status": "approved",
      "immutable": true,
      "path": "specs/008-expedition-example-domain/spec.md",
      "governs": [
        "examples/",
        "contracts/examples/",
        "workflows/examples/"
      ]
    },
    {
      "id": "009-expedition-example-artifacts",
      "version": "1.0.0",
      "status": "approved",
      "immutable": true,
      "path": "specs/009-expedition-example-artifacts/spec.md",
      "governs": [
        "contracts/examples/",
        "workflows/examples/"
      ]
    },
    {
      "id": "010-runtime-state-machine",
      "version": "1.0.0",
      "status": "approved",
      "immutable": true,
      "path": "specs/010-runtime-state-machine/spec.md",
      "governs": [
        "crates/cogolo-runtime/",
        "crates/traverse-runtime/"
      ]
    },
    {
      "id": "013-browser-runtime-subscription",
      "version": "1.0.0",
      "status": "approved",
      "immutable": true,
      "path": "specs/013-browser-runtime-subscription/spec.md",
      "governs": [
        "crates/cogolo-runtime/",
        "crates/traverse-runtime/"
      ]
    },
    {
      "id": "011-event-registry",
      "version": "1.0.0",
      "status": "approved",
      "immutable": true,
      "path": "specs/011-event-registry/spec.md",
      "governs": [
        "crates/cogolo-registry/",
        "crates/traverse-registry/"
      ]
    },
    {
      "id": "018-event-driven-composition",
      "version": "1.0.0",
      "status": "approved",
      "immutable": true,
      "path": "specs/018-event-driven-composition/spec.md",
      "governs": [
        "crates/cogolo-runtime/",
        "crates/traverse-runtime/",
        "crates/cogolo-registry/",
        "crates/traverse-registry/"
      ]
    }
  ]
}
